slrzd/__init__.py
slrzd-0.0.10.dist-info/LICENSE
slrzd-0.0.10.dist-info/WHEEL
slrzd-0.0.10.dist-info/METADATA
slrzd-0.0.10.dist-info/RECORD
