Metadata-Version: 2.1
Name: slrzd
Version: 0.0.10
Summary: Solarize everything
License: AGPL-3.0-or-later
Author: Angelo Gladding
Author-email: angelo@ragt.ag
Requires-Python: >=3.9,<3.11
Classifier: License :: OSI Approved :: GNU Affero General Public License v3 or later (AGPLv3+)
Classifier: Programming Language :: Python :: 3
Classifier: Programming Language :: Python :: 3.9
Requires-Dist: Pygments (>=2.11.2,<3.0.0)
